zcatalyst_cliq/__init__.py
zcatalyst_cliq/__version__.py
zcatalyst_cliq/_constants.py
zcatalyst_cliq/_handler.py
zcatalyst_cliq/_handler_util.py
zcatalyst_cliq/_utils.py
zcatalyst_cliq/api_service.py
zcatalyst_cliq/bot_handler.py
zcatalyst_cliq/cliq_connector.py
zcatalyst_cliq/command_handler.py
zcatalyst_cliq/error.py
zcatalyst_cliq/extension_handler.py
zcatalyst_cliq/function_handler.py
zcatalyst_cliq/handler_response.py
zcatalyst_cliq/link_preview_handler.py
zcatalyst_cliq/message_action_handler.py
zcatalyst_cliq/request_types.py
zcatalyst_cliq/response_types.py
zcatalyst_cliq/widget_handler.py
zcatalyst_cliq-1.0.0.dist-info/LICENSE
zcatalyst_cliq-1.0.0.dist-info/METADATA
zcatalyst_cliq-1.0.0.dist-info/WHEEL
zcatalyst_cliq-1.0.0.dist-info/top_level.txt
zcatalyst_cliq-1.0.0.dist-info/RECORD
